countersign/__init__.py
countersign/core.py
countersign/passphrase.py
countersign/password.py
countersign-0.1.0.dist-info/METADATA
countersign-0.1.0.dist-info/WHEEL
countersign-0.1.0.dist-info/top_level.txt
countersign-0.1.0.dist-info/RECORD
