Metadata-Version: 2.1
Name: countersign
Version: 0.1.0
Summary: Lightweight API that helps consumers generate random passwords and phrases.
Home-page: https://github.com/JSextonn/countersign.git
Author: Justin Sexton
Author-email: justinsexton.dev@gmail.com
License: MIT
Keywords: password,password-generator,library
Platform: UNKNOWN
Classifier: Programming Language :: Python :: 3
Classifier: License :: OSI Approved :: MIT License
Classifier: Operating System :: OS Independent
Requires-Python: >=3.6
